jax_loop_utils/__init__.py
jax_loop_utils/asynclib.py
jax_loop_utils/metrics.py
jax_loop_utils/parameter_overview.py
jax_loop_utils/periodic_actions.py
jax_loop_utils/profiler.py
jax_loop_utils/py.typed
jax_loop_utils/values.py
jax_loop_utils/internal/__init__.py
jax_loop_utils/internal/utils.py
jax_loop_utils/internal/flax/README.md
jax_loop_utils/internal/flax/__init__.py
jax_loop_utils/internal/flax/struct.py
jax_loop_utils/metric_writers/__init__.py
jax_loop_utils/metric_writers/async_writer.py
jax_loop_utils/metric_writers/interface.py
jax_loop_utils/metric_writers/keep_last_writer.py
jax_loop_utils/metric_writers/logging_writer.py
jax_loop_utils/metric_writers/memory_writer.py
jax_loop_utils/metric_writers/multi_writer.py
jax_loop_utils/metric_writers/noop_writer.py
jax_loop_utils/metric_writers/prefix_suffix_writer.py
jax_loop_utils/metric_writers/utils.py
jax_loop_utils/metric_writers/_audio_video/__init__.py
jax_loop_utils/metric_writers/_audio_video/audio_video.py
jax_loop_utils/metric_writers/mlflow/__init__.py
jax_loop_utils/metric_writers/mlflow/metric_writer.py
jax_loop_utils/metric_writers/tf/__init__.py
jax_loop_utils/metric_writers/tf/summary_writer.py
jax_loop_utils/metric_writers/torch/__init__.py
jax_loop_utils/metric_writers/torch/tensorboard_writer.py
jax_loop_utils/platform/__init__.py
jax_loop_utils/platform/interface.py
jax_loop_utils/platform/local.py
jax_loop_utils-0.0.14.dist-info/METADATA
jax_loop_utils-0.0.14.dist-info/WHEEL
jax_loop_utils-0.0.14.dist-info/licenses/LICENSE
jax_loop_utils-0.0.14.dist-info/RECORD
