Metadata-Version: 2.4
Name: jax_loop_utils
Version: 0.0.14
Summary: Libraries for ML training loops in JAX.
Project-URL: Homepage, http://github.com/garymm/jax_loop_utils
Author-email: Gary Miguel <garymm@garymm.org>
License: Apache 2.0
License-File: LICENSE
Keywords: JAX,machine learning
Classifier: Development Status :: 4 - Beta
Classifier: Intended Audience :: Developers
Classifier: Intended Audience :: Science/Research
Classifier: License :: OSI Approved :: Apache Software License
Classifier: Programming Language :: Python
Classifier: Topic :: Scientific/Engineering :: Artificial Intelligence
Requires-Python: >=3.11
Requires-Dist: absl-py
Requires-Dist: etils[epath,epy]
Requires-Dist: jax>=0.4.36
Requires-Dist: numpy
Requires-Dist: wrapt
Provides-Extra: audio-video
Requires-Dist: av>=14.0; extra == 'audio-video'
Provides-Extra: mlflow
Requires-Dist: mlflow-skinny>=2.0; extra == 'mlflow'
Requires-Dist: pillow; extra == 'mlflow'
Provides-Extra: synopsis
Requires-Dist: chex; extra == 'synopsis'
Requires-Dist: flax; extra == 'synopsis'
Requires-Dist: ipykernel; extra == 'synopsis'
Requires-Dist: matplotlib; extra == 'synopsis'
Provides-Extra: tensorflow
Requires-Dist: tensorflow>=2.12; extra == 'tensorflow'
Provides-Extra: torch
Requires-Dist: torch>=2.0; extra == 'torch'
